qvantum/__init__.py
qvantum/bloch.py
qvantum/check_bloch.py
qvantum/check_circuit.py
qvantum/check_gate.py
qvantum/check_layer.py
qvantum/check_qubit.py
qvantum/check_register.py
qvantum/circuit.py
qvantum/gate.py
qvantum/layer.py
qvantum/qubit.py
qvantum/register.py
qvantum-0.97.dist-info/METADATA
qvantum-0.97.dist-info/WHEEL
qvantum-0.97.dist-info/top_level.txt
qvantum-0.97.dist-info/RECORD
