Metadata-Version: 2.1
Name: qvantum
Version: 0.97
Summary: Python package for quantum computing
Home-page: http://github.com/vorpex/qvantum
Author: Adam Sohonyai & Roland Sztaho
Author-email: sohonyai.adam@gmail.com
Maintainer: Adam Sohonyai
Maintainer-email: sohonyai.adam@gmail.com
License: MIT
Keywords: python quantum computing process
Platform: UNKNOWN
Classifier: Development Status :: 4 - Beta
Classifier: Intended Audience :: Developers
Classifier: Intended Audience :: Education
Classifier: Intended Audience :: Science/Research
Classifier: License :: OSI Approved :: MIT License
Classifier: Operating System :: OS Independent
Classifier: Programming Language :: Python :: 2
Classifier: Programming Language :: Python :: 3
Requires-Dist: matplotlib
Requires-Dist: numpy
